Metadata-Version: 2.1
Name: odoo-addon-account_invoice_merge_attachment
Version: 16.0.1.0.0.3
Summary: Consider attachment during invoice merge process
Home-page: https://github.com/OCA/account-invoicing
Author: ACSONE SA/NV, Odoo Community Association (OCA)
Author-email: support@odoo-community.org
License: AGPL-3
Classifier: Programming Language :: Python
Classifier: Framework :: Odoo
Classifier: Framework :: Odoo :: 16.0
Classifier: License :: OSI Approved :: GNU Affero General Public License v3
Requires-Python: >=3.10
Requires-Dist: odoo-addon-account-invoice-merge<16.1dev,>=16.0dev
Requires-Dist: odoo<16.1dev,>=16.0a
